Metadata-Version: 1.1
Name: starlette-jwt
Version: 0.1.4
Summary: A JSON Web Token Middleware for Starlette
Home-page: https://github.com/amitripshtos/starlette-jwt
Author: Amit Ripshtos
Author-email: UNKNOWN
License: BSD
Keywords: starlette_jwt
Platform: UNKNOWN
Classifier: Development Status :: 2 - Pre-Alpha
Classifier: Intended Audience :: Developers
Classifier: Natural Language :: English
Classifier: Programming Language :: Python :: 3
Classifier: Programming Language :: Python :: 3.5
Classifier: Programming Language :: Python :: 3.6
Classifier: Programming Language :: Python :: 3.7
